{
  "uuid": "0e666794-80de-47e5-8cbc-7807fa512158",
  "url": "https://mahou-contents.mbs.jp/shops/0e666794-80de-47e5-8cbc-7807fa512158",
  "name": "梅田珈琲館YC",
  "address": "大阪市北区角田町9-2 新梅田食道街 1F",
  "tel": "06-6313-4462",
  "businessHours": "7:00～23:00",
  "regularHoliday": "年中無休",
  "nearStation": "大阪梅田",
  "comment": "営業時間・定休日などの詳細は公式サイトにてご確認ください。 2024年10月2日(水)の情報です。",
  "cast": "水野真紀 長野博 ロザン ゲスト：銀シャリ VTRゲスト：エルフ 間寛平 からし蓮根 松村沙友理",
  "broadcastInfo": [
    "2024年10月2日(水)放送 御堂筋 新旧たまごグルメ",
    "新旧たまごグルメ",
    "巻き部門 旧",
    "梅田珈琲館YC"
  ]
}