{
  "uuid": "44cf7b23-58ce-4bc8-a51b-f5210f604c4e",
  "url": "https://mahou-contents.mbs.jp/shops/44cf7b23-58ce-4bc8-a51b-f5210f604c4e",
  "name": "キャピタル東洋亭 本店",
  "address": "京都市北区上賀茂岩ヶ垣内町28番地3",
  "tel": "075-722-2121",
  "businessHours": "【ランチ】11:00～17:00【ディナー】17:00～22:00",
  "regularHoliday": "12月25日～1月1日",
  "nearStation": "北山",
  "comment": "※営業時間・定休日などの詳細は公式サイトにてご確認ください。 2024年12月18日(水)の情報です。",
  "cast": "水野真紀 長野博 ロザン 三ツ廣政輝アナウンサー ゲスト：キャイ～ン VTRゲスト：河合郁人 田村裕",
  "broadcastInfo": [
    "2024年12月18日(水)放送 関西ミシュランシェフ激推し！ガチ通いチェーン7連発",
    "関西ミシュランシェフ激推し！ガチ通いチェーン7連発",
    "キャピタル東洋亭"
  ]
}