{
  "uuid": "7f496f46-2181-4989-a777-b5d0c565dead",
  "url": "https://mahou-contents.mbs.jp/shops/7f496f46-2181-4989-a777-b5d0c565dead",
  "name": "重亭",
  "address": "大阪市中央区難波3-1-30",
  "tel": "06-6641-5719",
  "businessHours": "11:30～15:00(LO 14:30)、16:30～20:00(LO 19:30)",
  "regularHoliday": "水曜日、他不定休",
  "nearStation": "近鉄日本橋",
  "comment": "営業時間・定休日などの詳細は公式サイトにてご確認ください。 2024年9月18日(水)の情報です。",
  "cast": "水野真紀 長野博 ロザン 三ツ廣政輝アナウンサー ゲスト：八嶋智人 VTRゲスト：香西かおり くっきー！ 間寛平 アキナ",
  "broadcastInfo": [
    "2024年9月18日(水)放送 なんばLOVER50人に聞く 外さんグルメMAP2024",
    "なんばLOVER50人に聞く",
    "外さんグルメMAP",
    "2024"
  ]
}